src/multicamcomposepro/__init__.py
src/multicamcomposepro/augment.py
src/multicamcomposepro/camera.py
src/multicamcomposepro/main.py
src/multicamcomposepro/utils.py
multi_cam_compose_pro_RUFSHOD-0.0.1.dist-info/LICENSE
multi_cam_compose_pro_RUFSHOD-0.0.1.dist-info/METADATA
multi_cam_compose_pro_RUFSHOD-0.0.1.dist-info/WHEEL
multi_cam_compose_pro_RUFSHOD-0.0.1.dist-info/top_level.txt
multi_cam_compose_pro_RUFSHOD-0.0.1.dist-info/RECORD
