Metadata-Version: 2.1
Name: multi_cam_compose_pro_RUFSHOD
Version: 0.0.1
Summary: PLACEHOLDER: multi_cam_compose_pro is used to take images in order to train a model
Author-email: Wlinds & Rufshod <alexander@11a.se>
Project-URL: Homepage, https://github.com/wlinds/mccp
Project-URL: Bug Tracker, https://github.com/wlinds/mccp/issues
Classifier: Programming Language :: Python :: 3
Classifier: License :: OSI Approved :: MIT License
Classifier: Operating System :: OS Independent
Requires-Python: >=3.7
License-File: LICENSE
Requires-Dist: opencv-python
